visible_model_runner/ConfigOption.py
visible_model_runner/DeltaGenerator.py
visible_model_runner/ForwardMsgCache.py
visible_model_runner/MediaFileManager.py
visible_model_runner/Report.py
visible_model_runner/ReportQueue.py
visible_model_runner/ReportSession.py
visible_model_runner/ReportThread.py
visible_model_runner/ScriptRequestQueue.py
visible_model_runner/ScriptRunner.py
visible_model_runner/UploadedFileManager.py
visible_model_runner/__init__.py
visible_model_runner/bootstrap.py
visible_model_runner/caching.py
visible_model_runner/case_converters.py
visible_model_runner/cli.py
visible_model_runner/code_util.py
visible_model_runner/config.py
visible_model_runner/credentials.py
visible_model_runner/cursor.py
visible_model_runner/development.py
visible_model_runner/env_util.py
visible_model_runner/error_util.py
visible_model_runner/errors.py
visible_model_runner/file_util.py
visible_model_runner/folder_black_list.py
visible_model_runner/hashing.py
visible_model_runner/js_number.py
visible_model_runner/logger.py
visible_model_runner/magic.py
visible_model_runner/metrics.py
visible_model_runner/net_util.py
visible_model_runner/policy.py
visible_model_runner/source_util.py
visible_model_runner/string_util.py
visible_model_runner/temporary_directory.py
visible_model_runner/type_util.py
visible_model_runner/url_util.py
visible_model_runner/util.py
visible_model_runner/version.py
visible_model_runner/widgets.py
visible_model_runner/elements/__init__.py
visible_model_runner/elements/altair.py
visible_model_runner/elements/bokeh_chart.py
visible_model_runner/elements/data_frame_proto.py
visible_model_runner/elements/deck_gl.py
visible_model_runner/elements/deck_gl_json_chart.py
visible_model_runner/elements/doc_string.py
visible_model_runner/elements/exception_proto.py
visible_model_runner/elements/graphviz_chart.py
visible_model_runner/elements/image_proto.py
visible_model_runner/elements/map.py
visible_model_runner/elements/media_proto.py
visible_model_runner-0.0.2.dist-info/METADATA
visible_model_runner-0.0.2.dist-info/WHEEL
visible_model_runner-0.0.2.dist-info/entry_points.txt
visible_model_runner-0.0.2.dist-info/top_level.txt
visible_model_runner-0.0.2.dist-info/RECORD
