Metadata-Version: 2.1
Name: visible-model-runner
Version: 0.0.2
Summary: Frontend library for machine learning engineers
Home-page: https://visible_model_runner.io
Author: Streamlit Inc
Author-email: 415296473@qq.com
License: Apache 2
Platform: UNKNOWN
Requires-Python: >=3.6
Requires-Dist: altair (>=3.2.0)
Requires-Dist: astor
Requires-Dist: base58
Requires-Dist: blinker
Requires-Dist: boto3
Requires-Dist: botocore (>=1.13.44)
Requires-Dist: cachetools (>=4.0)
Requires-Dist: click (>=7.0)
Requires-Dist: enum-compat
Requires-Dist: numpy
Requires-Dist: packaging
Requires-Dist: pandas (>=0.21.0)
Requires-Dist: pillow (>=6.2.0)
Requires-Dist: protobuf (>=3.6.0)
Requires-Dist: pydeck (>=0.1.dev5)
Requires-Dist: python-dateutil
Requires-Dist: requests
Requires-Dist: toml
Requires-Dist: tornado (<6.0,>=5.0)
Requires-Dist: tzlocal
Requires-Dist: validators
Requires-Dist: watchdog
